dbs/__init__.py
dbs/__main__.py
dbs_task/__init__.py
dbs_todo-0.6.2.dist-info/licenses/LICENSE
dbsui/__init__.py
dbsui/__main__.py
dbs_todo-0.6.2.dist-info/METADATA
dbs_todo-0.6.2.dist-info/WHEEL
dbs_todo-0.6.2.dist-info/entry_points.txt
dbs_todo-0.6.2.dist-info/top_level.txt
dbs_todo-0.6.2.dist-info/RECORD
