Metadata-Version: 2.4
Name: dbs-todo
Version: 0.6.2
Summary: Dain-Bread Simple TODO list
Home-page: https://github.com/ahs3/dbs
Author: Al Stone
Author-email: ahs3@ahs3.net
Project-URL: Bug Tracker, https://github.com/ahs3/dbs/issues
Classifier: Programming Language :: Python :: 3
Classifier: License :: OSI Approved :: MIT License
Classifier: Operating System :: OS Independent
Requires-Python: >=3.7
License-File: LICENSE
Dynamic: license-file
